[
  {
    "_type": "url",
    "url": "https://www.youtube.com/playlist?list=PLZEkgohG7k7o1jwm5FHUI0Jkh1-14bKce",
    "ie_key": "YoutubeTab",
    "id": "PLZEkgohG7k7o1jwm5FHUI0Jkh1-14bKce",
    "title": "\"Ask Yourself\" (Criticism of the Youtuber known as…)"
  },
  {
    "_type": "url",
    "url": "https://www.youtube.com/playlist?list=PLZEkgohG7k7r2yc18ZAehpfiLBtBwmNQh",
    "ie_key": "YoutubeTab",
    "id": "PLZEkgohG7k7r2yc18ZAehpfiLBtBwmNQh",
    "title": "\"On Community\" (a Vegan Manifesto) in Many Languages"
  },
  {
    "_type": "url",
    "url": "https://www.youtube.com/playlist?list=PLZEkgohG7k7psJ2wpIdyyFH9EfW94-cdT",
    "ie_key": "YoutubeTab",
    "id": "PLZEkgohG7k7psJ2wpIdyyFH9EfW94-cdT",
    "title": "\"The Left\""
  },
  {
    "_type": "url",
    "url": "https://www.youtube.com/playlist?list=PLZEkgohG7k7q2LiHf4ObanurG11LpGPVJ",
    "ie_key": "YoutubeTab",
    "id": "PLZEkgohG7k7q2LiHf4ObanurG11LpGPVJ",
    "title": "(Comedic) Vegan Masterpiece Theater"
  },
  {
    "_type": "url",
    "url": "https://www.youtube.com/playlist?list=PLZEkgohG7k7rg8v_t6cpD964osvs2xJk0",
    "ie_key": "YoutubeTab",
    "id": "PLZEkgohG7k7rg8v_t6cpD964osvs2xJk0",
    "title": "AOC, Alexandria Ocasio-Cortez"
  },
  {
    "_type": "url",
    "url": "https://www.youtube.com/playlist?list=PLZEkgohG7k7oK5ShvyvAswb-3lSWjlQe6",
    "ie_key": "YoutubeTab",
    "id": "PLZEkgohG7k7oK5ShvyvAswb-3lSWjlQe6",
    "title": "ASOIAF (\"A Song of Ice and Fire\" & \"Game of Thrones\")"
  },
  {
    "_type": "url",
    "url": "https://www.youtube.com/playlist?list=PLZEkgohG7k7pHtoHQfLUtsCgbdbpcbRJ9",
    "ie_key": "YoutubeTab",
    "id": "PLZEkgohG7k7pHtoHQfLUtsCgbdbpcbRJ9",
    "title": "Aaron Yarmel, replies to"
  },
  {
    "_type": "url",
    "url": "https://www.youtube.com/playlist?list=PLZEkgohG7k7roNNGMARf3BPJj_1cB3IHN",
    "ie_key": "YoutubeTab",
    "id": "PLZEkgohG7k7roNNGMARf3BPJj_1cB3IHN",
    "title": "Advice nobody wants to hear."
  },
  {
    "_type": "url",
    "url": "https://www.youtube.com/playlist?list=PLZEkgohG7k7rCDejUL7t2n3UGBb-rP5-3",
    "ie_key": "YoutubeTab",
    "id": "PLZEkgohG7k7rCDejUL7t2n3UGBb-rP5-3",
    "title": "Alain de Botton & The School of Life, critique of"
  },
  {
    "_type": "url",
    "url": "https://www.youtube.com/playlist?list=PLZEkgohG7k7qU1WWi-h49Lvo_aZQ7MPAD",
    "ie_key": "YoutubeTab",
    "id": "PLZEkgohG7k7qU1WWi-h49Lvo_aZQ7MPAD",
    "title": "Ali Abdaal, critique of"
  },
  {
    "_type": "url",
    "url": "https://www.youtube.com/playlist?list=PLZEkgohG7k7oXk0AFX645IawPTFc8LvbE",
    "ie_key": "YoutubeTab",
    "id": "PLZEkgohG7k7oXk0AFX645IawPTFc8LvbE",
    "title": "Anarchism, critique of"
  },
  {
    "_type": "url",
    "url": "https://www.youtube.com/playlist?list=PLZEkgohG7k7r8wpiNhnHYXV0Q-easm_oq",
    "ie_key": "YoutubeTab",
    "id": "PLZEkgohG7k7r8wpiNhnHYXV0Q-easm_oq",
    "title": "Anna's Analysis, critique of"
  },
  {
    "_type": "url",
    "url": "https://www.youtube.com/playlist?list=PLZEkgohG7k7rgYYR4_CpHK2YimEiJGmrq",
    "ie_key": "YoutubeTab",
    "id": "PLZEkgohG7k7rgYYR4_CpHK2YimEiJGmrq",
    "title": "Anti-Anti-Natalism (Ecology & Having Kids)"
  },
  {
    "_type": "url",
    "url": "https://www.youtube.com/playlist?list=PLZEkgohG7k7rq7l8i6VGhFUrGAwTBoTS1",
    "ie_key": "YoutubeTab",
    "id": "PLZEkgohG7k7rq7l8i6VGhFUrGAwTBoTS1",
    "title": "Anti-AntiDepressants (Depression, etc.)"
  },
  {
    "_type": "url",
    "url": "https://www.youtube.com/playlist?list=PLZEkgohG7k7pJ5af8NAY0w1rx05oGlMjZ",
    "ie_key": "YoutubeTab",
    "id": "PLZEkgohG7k7pJ5af8NAY0w1rx05oGlMjZ",
    "title": "Aristotle, critique of"
  },
  {
    "_type": "url",
    "url": "https://www.youtube.com/playlist?list=PLZEkgohG7k7qveOlCsBIEyeJur1lAzwHB",
    "ie_key": "YoutubeTab",
    "id": "PLZEkgohG7k7qveOlCsBIEyeJur1lAzwHB",
    "title": "Atheist ❝Activists❞, critique of"
  },
  {
    "_type": "url",
    "url": "https://www.youtube.com/playlist?list=PLZEkgohG7k7r2KOvbCAIKvulmFOp1kRKc",
    "ie_key": "YoutubeTab",
    "id": "PLZEkgohG7k7r2KOvbCAIKvulmFOp1kRKc",
    "title": "Athens & Rome, Political Philosophy."
  },
  {
    "_type": "url",
    "url": "https://www.youtube.com/playlist?list=PLZEkgohG7k7o6fYFC3mhSCBtDLzIZsXNS",
    "ie_key": "YoutubeTab",
    "id": "PLZEkgohG7k7o6fYFC3mhSCBtDLzIZsXNS",
    "title": "Autobiographical (Eisel Mazard / à-bas-le-ciel)"
  },
  {
    "_type": "url",
    "url": "https://www.youtube.com/playlist?list=PLZEkgohG7k7rtpI_3UY6VKORCzQcgjBxp",
    "ie_key": "YoutubeTab",
    "id": "PLZEkgohG7k7rtpI_3UY6VKORCzQcgjBxp",
    "title": "BLM: Black Lives Matter"
  },
  {
    "_type": "url",
    "url": "https://www.youtube.com/playlist?list=PLZEkgohG7k7pFWDaGfuW-k3SSlJ6f45lx",
    "ie_key": "YoutubeTab",
    "id": "PLZEkgohG7k7pFWDaGfuW-k3SSlJ6f45lx",
    "title": "Based Zeus vs. Based Pawn"
  },
  {
    "_type": "url",
    "url": "https://www.youtube.com/playlist?list=PLZEkgohG7k7oR4VNW2G5jXVTzc--47Ry_",
    "ie_key": "YoutubeTab",
    "id": "PLZEkgohG7k7oR4VNW2G5jXVTzc--47Ry_",
    "title": "Beauty, the tyranny of beauty"
  },
  {
    "_type": "url",
    "url": "https://www.youtube.com/playlist?list=PLZEkgohG7k7qC7zcRcZfOelafM8QByK4h",
    "ie_key": "YoutubeTab",
    "id": "PLZEkgohG7k7qC7zcRcZfOelafM8QByK4h",
    "title": "Bernie Sanders, analysis, critique, commentary."
  },
  {
    "_type": "url",
    "url": "https://www.youtube.com/playlist?list=PLZEkgohG7k7qF8EvPQaXV7Q8REEjk7xK_",
    "ie_key": "YoutubeTab",
    "id": "PLZEkgohG7k7qF8EvPQaXV7Q8REEjk7xK_",
    "title": "Bonny Rebecca (ex-vegan icon?)"
  },
  {
    "_type": "url",
    "url": "https://www.youtube.com/playlist?list=PLZEkgohG7k7p-Gh60Ko_nM6-xSU3X20tU",
    "ie_key": "YoutubeTab",
    "id": "PLZEkgohG7k7p-Gh60Ko_nM6-xSU3X20tU",
    "title": "Book Reviews (Politics / Vegan Politics)"
  },
  {
    "_type": "url",
    "url": "https://www.youtube.com/playlist?list=PLZEkgohG7k7okWjcSH0HnY6BUbMkELHEG",
    "ie_key": "YoutubeTab",
    "id": "PLZEkgohG7k7okWjcSH0HnY6BUbMkELHEG",
    "title": "Brass Tacks (Vegan Political Organization NOW)"
  },
  {
    "_type": "url",
    "url": "https://www.youtube.com/playlist?list=PLZEkgohG7k7o2YfYZ4gXgp7pWW1zeI_6Z",
    "ie_key": "YoutubeTab",
    "id": "PLZEkgohG7k7o2YfYZ4gXgp7pWW1zeI_6Z",
    "title": "Buddhism (A Pali Scholar's Perspective)"
  },
  {
    "_type": "url",
    "url": "https://www.youtube.com/playlist?list=PLZEkgohG7k7ph4GjbjjUHDnImp9NpHyDE",
    "ie_key": "YoutubeTab",
    "id": "PLZEkgohG7k7ph4GjbjjUHDnImp9NpHyDE",
    "title": "Canada (Canadian Politics)"
  },
  {
    "_type": "url",
    "url": "https://www.youtube.com/playlist?list=PLZEkgohG7k7oMkZDMZDe6XZqYQCZcRVmg",
    "ie_key": "YoutubeTab",
    "id": "PLZEkgohG7k7oMkZDMZDe6XZqYQCZcRVmg",
    "title": "Central Asia & Xinjiang (新疆)"
  },
  {
    "_type": "url",
    "url": "https://www.youtube.com/playlist?list=PLZEkgohG7k7pyEf4fEGlABNmlPLubSTJZ",
    "ie_key": "YoutubeTab",
    "id": "PLZEkgohG7k7pyEf4fEGlABNmlPLubSTJZ",
    "title": "China & Taiwan (Contemporary Politics, Society, Culture)"
  },
  {
    "_type": "url",
    "url": "https://www.youtube.com/playlist?list=PLZEkgohG7k7oAfJuTCDqE89L42rt6eu0N",
    "ie_key": "YoutubeTab",
    "id": "PLZEkgohG7k7oAfJuTCDqE89L42rt6eu0N",
    "title": "China, ancient or, at least, pre-modern."
  },
  {
    "_type": "url",
    "url": "https://www.youtube.com/playlist?list=PLZEkgohG7k7qDwvsV2lnuOz_-B9RGDO_Y",
    "ie_key": "YoutubeTab",
    "id": "PLZEkgohG7k7qDwvsV2lnuOz_-B9RGDO_Y",
    "title": "Civil Disobedience, Critique Of"
  },
  {
    "_type": "url",
    "url": "https://www.youtube.com/playlist?list=PLZEkgohG7k7qe-cE12jCQvLlWkXG0E8N_",
    "ie_key": "YoutubeTab",
    "id": "PLZEkgohG7k7qe-cE12jCQvLlWkXG0E8N_",
    "title": "Claire Michelle (Responses to)"
  },
  {
    "_type": "url",
    "url": "https://www.youtube.com/playlist?list=PLZEkgohG7k7qp88PUxw93A5a0Ig52jnvL",
    "ie_key": "YoutubeTab",
    "id": "PLZEkgohG7k7qp88PUxw93A5a0Ig52jnvL",
    "title": "Conservativism & Republicanism, the future of?"
  },
  {
    "_type": "url",
    "url": "https://www.youtube.com/playlist?list=PLZEkgohG7k7pW5ExxLGtLJ5tgEk7XT5c1",
    "ie_key": "YoutubeTab",
    "id": "PLZEkgohG7k7pW5ExxLGtLJ5tgEk7XT5c1",
    "title": "Cosmic Skeptic, critique of"
  },
  {
    "_type": "url",
    "url": "https://www.youtube.com/playlist?list=PLZEkgohG7k7r62K2IxcYRJZTGLc_MulOr",
    "ie_key": "YoutubeTab",
    "id": "PLZEkgohG7k7r62K2IxcYRJZTGLc_MulOr",
    "title": "Criticism of Mic. the Vegan"
  },
  {
    "_type": "url",
    "url": "https://www.youtube.com/playlist?list=PLZEkgohG7k7rkhNcwBKOJExsypJnnMaxd",
    "ie_key": "YoutubeTab",
    "id": "PLZEkgohG7k7rkhNcwBKOJExsypJnnMaxd",
    "title": "Critique of Gor / Goreans / John Norman"
  },
  {
    "_type": "url",
    "url": "https://www.youtube.com/playlist?list=PLZEkgohG7k7olFftbvop4Ks1AwxhFwD_7",
    "ie_key": "YoutubeTab",
    "id": "PLZEkgohG7k7olFftbvop4Ks1AwxhFwD_7",
    "title": "Critique of John St Julien Baba Wanyama"
  },
  {
    "_type": "url",
    "url": "https://www.youtube.com/playlist?list=PLZEkgohG7k7oVSdOjYo1lQIxmypM3Z0wC",
    "ie_key": "YoutubeTab",
    "id": "PLZEkgohG7k7oVSdOjYo1lQIxmypM3Z0wC",
    "title": "Critique of Karl Marx, Communist Manifesto (series)"
  },
  {
    "_type": "url",
    "url": "https://www.youtube.com/playlist?list=PLZEkgohG7k7rbtNl3Zv7ZEuxx38IhRqtu",
    "ie_key": "YoutubeTab",
    "id": "PLZEkgohG7k7rbtNl3Zv7ZEuxx38IhRqtu",
    "title": "Critique of the University of Victoria, B.C., Canada"
  },
  {
    "_type": "url",
    "url": "https://www.youtube.com/playlist?list=PLZEkgohG7k7o2tfT6y8w7OeQmnAt_42mn",
    "ie_key": "YoutubeTab",
    "id": "PLZEkgohG7k7o2tfT6y8w7OeQmnAt_42mn",
    "title": "Cube of Truth  / Anonymous for the Voiceless"
  },
  {
    "_type": "url",
    "url": "https://www.youtube.com/playlist?list=PLZEkgohG7k7rgv0EROkU-zP7Q0VWIuU1z",
    "ie_key": "YoutubeTab",
    "id": "PLZEkgohG7k7rgv0EROkU-zP7Q0VWIuU1z",
    "title": "DRUGS. #QuitEverything"
  },
  {
    "_type": "url",
    "url": "https://www.youtube.com/playlist?list=PLZEkgohG7k7qKC2uly_QsAhqK0-IH7k5e",
    "ie_key": "YoutubeTab",
    "id": "PLZEkgohG7k7qKC2uly_QsAhqK0-IH7k5e",
    "title": "Determinism, critique of"
  },
  {
    "_type": "url",
    "url": "https://www.youtube.com/playlist?list=PLZEkgohG7k7okP_5OlRvvUwHGHqSALZ0n",
    "ie_key": "YoutubeTab",
    "id": "PLZEkgohG7k7okP_5OlRvvUwHGHqSALZ0n",
    "title": "Divorce (My First Wife)"
  },
  {
    "_type": "url",
    "url": "https://www.youtube.com/playlist?list=PLZEkgohG7k7rpxzjaIVXoMvvVOrNU19VG",
    "ie_key": "YoutubeTab",
    "id": "PLZEkgohG7k7rpxzjaIVXoMvvVOrNU19VG",
    "title": "Domestication (A Vegan Perspective AGAINST Pet Ownership, etc.)"
  },
  {
    "_type": "url",
    "url": "https://www.youtube.com/playlist?list=PLZEkgohG7k7rnlpe1mrR7bnaQwSaBYfij",
    "ie_key": "YoutubeTab",
    "id": "PLZEkgohG7k7rnlpe1mrR7bnaQwSaBYfij",
    "title": "Durianrider: the Court Case."
  },
  {
    "_type": "url",
    "url": "https://www.youtube.com/playlist?list=PLZEkgohG7k7qhwg8QIrDTQu-GqKu8Rc4s",
    "ie_key": "YoutubeTab",
    "id": "PLZEkgohG7k7qhwg8QIrDTQu-GqKu8Rc4s",
    "title": "DxE: Critique of Direct Action Everywhere (Activism in Theory & Practice)"
  },
  {
    "_type": "url",
    "url": "https://www.youtube.com/playlist?list=PLZEkgohG7k7pSA8BC6yoB22Xwh9G5OJOu",
    "ie_key": "YoutubeTab",
    "id": "PLZEkgohG7k7pSA8BC6yoB22Xwh9G5OJOu",
    "title": "Earthling Ed, Critique of"
  },
  {
    "_type": "url",
    "url": "https://www.youtube.com/playlist?list=PLZEkgohG7k7o8ZnnQAhjW2GqzrpHNZaCA",
    "ie_key": "YoutubeTab",
    "id": "PLZEkgohG7k7o8ZnnQAhjW2GqzrpHNZaCA",
    "title": "Edyn Jacks, critique of Body Positivity"
  },
  {
    "_type": "url",
    "url": "https://www.youtube.com/playlist?list=PLZEkgohG7k7ofBbvKpJRRqxWk66IqBfFq",
    "ie_key": "YoutubeTab",
    "id": "PLZEkgohG7k7ofBbvKpJRRqxWk66IqBfFq",
    "title": "Elizabeth Warren, analysis, critique, commentary"
  },
  {
    "_type": "url",
    "url": "https://www.youtube.com/playlist?list=PLZEkgohG7k7omRHToP4xhGC7kSqWBoG0C",
    "ie_key": "YoutubeTab",
    "id": "PLZEkgohG7k7omRHToP4xhGC7kSqWBoG0C",
    "title": "Erin Janus, Critique Of"
  },
  {
    "_type": "url",
    "url": "https://www.youtube.com/playlist?list=PLZEkgohG7k7rE69S2fdmcRGJg2u4COrdr",
    "ie_key": "YoutubeTab",
    "id": "PLZEkgohG7k7rE69S2fdmcRGJg2u4COrdr",
    "title": "Exercise & Diet (In My Own Life)"
  },
  {
    "_type": "url",
    "url": "https://www.youtube.com/playlist?list=PLZEkgohG7k7p68P7TI5YuvQaVoGY-_Mxf",
    "ie_key": "YoutubeTab",
    "id": "PLZEkgohG7k7p68P7TI5YuvQaVoGY-_Mxf",
    "title": "Extinction Rebellion, critique of"
  },
  {
    "_type": "url",
    "url": "https://www.youtube.com/playlist?list=PLZEkgohG7k7rZM5Pkgrbw_8WtbBudQQpP",
    "ie_key": "YoutubeTab",
    "id": "PLZEkgohG7k7rZM5Pkgrbw_8WtbBudQQpP",
    "title": "Faith Goldy, Critique Of"
  },
  {
    "_type": "url",
    "url": "https://www.youtube.com/playlist?list=PLZEkgohG7k7qKU5jEcHTvLrH5h0WK0RLq",
    "ie_key": "YoutubeTab",
    "id": "PLZEkgohG7k7qKU5jEcHTvLrH5h0WK0RLq",
    "title": "France (political or personal commentary on)"
  },
  {
    "_type": "url",
    "url": "https://www.youtube.com/playlist?list=PLZEkgohG7k7rGTkNsYUTgoer0w6MiVczf",
    "ie_key": "YoutubeTab",
    "id": "PLZEkgohG7k7rGTkNsYUTgoer0w6MiVczf",
    "title": "Friendship, on the nature of"
  },
  {
    "_type": "url",
    "url": "https://www.youtube.com/playlist?list=PLZEkgohG7k7o4o6qZ8Vq3FZDuvHObYlXm",
    "ie_key": "YoutubeTab",
    "id": "PLZEkgohG7k7o4o6qZ8Vq3FZDuvHObYlXm",
    "title": "Gary Yourofsky, Critique Of"
  },
  {
    "_type": "url",
    "url": "https://www.youtube.com/playlist?list=PLZEkgohG7k7pRI_CEeHyKzhnhdIK8azD1",
    "ie_key": "YoutubeTab",
    "id": "PLZEkgohG7k7pRI_CEeHyKzhnhdIK8azD1",
    "title": "Hard On Politics (Not Quite Satire)"
  },
  {
    "_type": "url",
    "url": "https://www.youtube.com/playlist?list=PLZEkgohG7k7pTyuUvXJWTShGmmW_yScwu",
    "ie_key": "YoutubeTab",
    "id": "PLZEkgohG7k7pTyuUvXJWTShGmmW_yScwu",
    "title": "HasanAbi (Hasan Piker), Critique of"
  },
  {
    "_type": "url",
    "url": "https://www.youtube.com/playlist?list=PLZEkgohG7k7pTUBiqpNlsuTrcY9dNIJR0",
    "ie_key": "YoutubeTab",
    "id": "PLZEkgohG7k7pTUBiqpNlsuTrcY9dNIJR0",
    "title": "Hinduism, critique of"
  },
  {
    "_type": "url",
    "url": "https://www.youtube.com/playlist?list=PLZEkgohG7k7ogRyDdIAh757EGzOrGoLWs",
    "ie_key": "YoutubeTab",
    "id": "PLZEkgohG7k7ogRyDdIAh757EGzOrGoLWs",
    "title": "Historical Nihilism, 历史虚无主义, \"My Own\" Philosophy."
  },
  {
    "_type": "url",
    "url": "https://www.youtube.com/playlist?list=PLZEkgohG7k7rhqBBz4mv0LrrXCR4Yy-ae",
    "ie_key": "YoutubeTab",
    "id": "PLZEkgohG7k7rhqBBz4mv0LrrXCR4Yy-ae",
    "title": "Hitomi Mochizuki, commentary on"
  },
  {
    "_type": "url",
    "url": "https://www.youtube.com/playlist?list=PLZEkgohG7k7qiLiimIZDIgbaMqfPiS7iR",
    "ie_key": "YoutubeTab",
    "id": "PLZEkgohG7k7qiLiimIZDIgbaMqfPiS7iR",
    "title": "Idiocy! Vegans Can Be Idiots, Too."
  },
  {
    "_type": "url",
    "url": "https://www.youtube.com/playlist?list=PLZEkgohG7k7r4OpPGSnJw9bqpGLpphbv3",
    "ie_key": "YoutubeTab",
    "id": "PLZEkgohG7k7r4OpPGSnJw9bqpGLpphbv3",
    "title": "Immigration & Refugee Politics"
  },
  {
    "_type": "url",
    "url": "https://www.youtube.com/playlist?list=PLZEkgohG7k7ropCHZ4DDXXyi2ic2ygdb-",
    "ie_key": "YoutubeTab",
    "id": "PLZEkgohG7k7ropCHZ4DDXXyi2ic2ygdb-",
    "title": "Interviews with journalists / press / media"
  },
  {
    "_type": "url",
    "url": "https://www.youtube.com/playlist?list=PLZEkgohG7k7pj3W8hetYALCXSWkFcMGsG",
    "ie_key": "YoutubeTab",
    "id": "PLZEkgohG7k7pj3W8hetYALCXSWkFcMGsG",
    "title": "Izzy Davis, Replies To."
  },
  {
    "_type": "url",
    "url": "https://www.youtube.com/playlist?list=PLZEkgohG7k7oqGCWCnUbG-K_HdoyIY25u",
    "ie_key": "YoutubeTab",
    "id": "PLZEkgohG7k7oqGCWCnUbG-K_HdoyIY25u",
    "title": "Jaclyn Glenn, critique of"
  },
  {
    "_type": "url",
    "url": "https://www.youtube.com/playlist?list=PLZEkgohG7k7qe6xfC8ukqf7oUptd1Ajyk",
    "ie_key": "YoutubeTab",
    "id": "PLZEkgohG7k7qe6xfC8ukqf7oUptd1Ajyk",
    "title": "James Aspey, critique of"
  },
  {
    "_type": "url",
    "url": "https://www.youtube.com/playlist?list=PLZEkgohG7k7oTKn0Jg5Z_g18qqbeEPYIF",
    "ie_key": "YoutubeTab",
    "id": "PLZEkgohG7k7oTKn0Jg5Z_g18qqbeEPYIF",
    "title": "Jenna Marbles, Critique of"
  },
  {
    "_type": "url",
    "url": "https://www.youtube.com/playlist?list=PLZEkgohG7k7papx57DcQ4s10xQZbQH0fR",
    "ie_key": "YoutubeTab",
    "id": "PLZEkgohG7k7papx57DcQ4s10xQZbQH0fR",
    "title": "Joe Biden, critique of"
  },
  {
    "_type": "url",
    "url": "https://www.youtube.com/playlist?list=PLZEkgohG7k7obhv-XTlcjGHFGG_xaWw2T",
    "ie_key": "YoutubeTab",
    "id": "PLZEkgohG7k7obhv-XTlcjGHFGG_xaWw2T",
    "title": "Jon Venus, critique of"
  },
  {
    "_type": "url",
    "url": "https://www.youtube.com/playlist?list=PLZEkgohG7k7qq2IBKKT1BOXXo-3K7QuXE",
    "ie_key": "YoutubeTab",
    "id": "PLZEkgohG7k7qq2IBKKT1BOXXo-3K7QuXE",
    "title": "Jordan Peterson (Critiques Of)"
  },
  {
    "_type": "url",
    "url": "https://www.youtube.com/playlist?list=PLZEkgohG7k7q_OzvPPcr011_McIlULh0-",
    "ie_key": "YoutubeTab",
    "id": "PLZEkgohG7k7q_OzvPPcr011_McIlULh0-",
    "title": "Judaism, critique of"
  },
  {
    "_type": "url",
    "url": "https://www.youtube.com/playlist?list=PLZEkgohG7k7qWGJKE846RzwedO90xbyJx",
    "ie_key": "YoutubeTab",
    "id": "PLZEkgohG7k7qWGJKE846RzwedO90xbyJx",
    "title": "Kalel Kitten / Kalel Cullen, Critique of"
  },
  {
    "_type": "url",
    "url": "https://www.youtube.com/playlist?list=PLZEkgohG7k7p6MLNDYyFTgotUhetCO6Lb",
    "ie_key": "YoutubeTab",
    "id": "PLZEkgohG7k7p6MLNDYyFTgotUhetCO6Lb",
    "title": "KanadaJin3 (Japan, Islam & Canada)"
  },
  {
    "_type": "url",
    "url": "https://www.youtube.com/playlist?list=PLZEkgohG7k7oidzaEDXLaR2cjwTsFmuzk",
    "ie_key": "YoutubeTab",
    "id": "PLZEkgohG7k7oidzaEDXLaR2cjwTsFmuzk",
    "title": "Keeping it Real: Honesty as the Main Subject."
  },
  {
    "_type": "url",
    "url": "https://www.youtube.com/playlist?list=PLZEkgohG7k7oxSZgO50bc0BGSXy3hErls",
    "ie_key": "YoutubeTab",
    "id": "PLZEkgohG7k7oxSZgO50bc0BGSXy3hErls",
    "title": "Kristen Leo, critique of"
  },
  {
    "_type": "url",
    "url": "https://www.youtube.com/playlist?list=PLZEkgohG7k7rziMgl6iLHWQxC1yYutVRL",
    "ie_key": "YoutubeTab",
    "id": "PLZEkgohG7k7rziMgl6iLHWQxC1yYutVRL",
    "title": "Learning Chinese (Written Language + Spoken Language)"
  },
  {
    "_type": "url",
    "url": "https://www.youtube.com/playlist?list=PLZEkgohG7k7oosUBDGlI1FkKNThO6msUm",
    "ie_key": "YoutubeTab",
    "id": "PLZEkgohG7k7oosUBDGlI1FkKNThO6msUm",
    "title": "MadFit (Maddie Lymburner)"
  },
  {
    "_type": "url",
    "url": "https://www.youtube.com/playlist?list=PLZEkgohG7k7rooLjcKYe2G0n5Vw76Rk6O",
    "ie_key": "YoutubeTab",
    "id": "PLZEkgohG7k7rooLjcKYe2G0n5Vw76Rk6O",
    "title": "Mayim Bialik, critique of"
  },
  {
    "_type": "url",
    "url": "https://www.youtube.com/playlist?list=PLZEkgohG7k7piTjOcK4iA4RP6TlLj6-ss",
    "ie_key": "YoutubeTab",
    "id": "PLZEkgohG7k7piTjOcK4iA4RP6TlLj6-ss",
    "title": "Meditation is Bullshit (\"Scientific\" and/or Religious)"
  },
  {
    "_type": "url",
    "url": "https://www.youtube.com/playlist?list=PLZEkgohG7k7qPz0cttZX51ucLUnFfx2z_",
    "ie_key": "YoutubeTab",
    "id": "PLZEkgohG7k7qPz0cttZX51ucLUnFfx2z_",
    "title": "Mexie (Responses to / Criticisms Of)"
  },
  {
    "_type": "url",
    "url": "https://www.youtube.com/playlist?list=PLZEkgohG7k7pHannfLTihY0c_SXab7q9B",
    "ie_key": "YoutubeTab",
    "id": "PLZEkgohG7k7pHannfLTihY0c_SXab7q9B",
    "title": "Modern Greek, learning the language"
  },
  {
    "_type": "url",
    "url": "https://www.youtube.com/playlist?list=PLZEkgohG7k7oa7Qgn_pGhrUiQkvby1w1F",
    "ie_key": "YoutubeTab",
    "id": "PLZEkgohG7k7oa7Qgn_pGhrUiQkvby1w1F",
    "title": "Mutiny, when vegan followers rebel against their leaders"
  },
  {
    "_type": "url",
    "url": "https://www.youtube.com/playlist?list=PLZEkgohG7k7rhpA6eh18JUS6mJTRLNYie",
    "ie_key": "YoutubeTab",
    "id": "PLZEkgohG7k7rhpA6eh18JUS6mJTRLNYie",
    "title": "Nazis, Historical Critique of"
  },
  {
    "_type": "url",
    "url": "https://www.youtube.com/playlist?list=PLZEkgohG7k7qI2hI13WhGRfNW77IEqS5U",
    "ie_key": "YoutubeTab",
    "id": "PLZEkgohG7k7qI2hI13WhGRfNW77IEqS5U",
    "title": "Nina-and-Randa: Most Offensive Playlist Ever?"
  },
  {
    "_type": "url",
    "url": "https://www.youtube.com/playlist?list=PLZEkgohG7k7oTjFFRKI3ylZGnv87yYJtQ",
    "ie_key": "YoutubeTab",
    "id": "PLZEkgohG7k7oTjFFRKI3ylZGnv87yYJtQ",
    "title": "NonCompete, critique of"
  },
  {
    "_type": "url",
    "url": "https://www.youtube.com/playlist?list=PLZEkgohG7k7pat9tzkVr4UuTD57eOPEJ6",
    "ie_key": "YoutubeTab",
    "id": "PLZEkgohG7k7pat9tzkVr4UuTD57eOPEJ6",
    "title": "Norvegan is Lying to You"
  },
  {
    "_type": "url",
    "url": "https://www.youtube.com/playlist?list=PLZEkgohG7k7qVBa-4z7jr-gAtxQRIIMYD",
    "ie_key": "YoutubeTab",
    "id": "PLZEkgohG7k7qVBa-4z7jr-gAtxQRIIMYD",
    "title": "On Capitalism (the political and economic system itself)"
  },
  {
    "_type": "url",
    "url": "https://www.youtube.com/playlist?list=PLZEkgohG7k7pUwuwKFQt-VYNH5MKnDoI4",
    "ie_key": "YoutubeTab",
    "id": "PLZEkgohG7k7pUwuwKFQt-VYNH5MKnDoI4",
    "title": "On Peer Review (Critique of Academia)"
  },
  {
    "_type": "url",
    "url": "https://www.youtube.com/playlist?list=PLZEkgohG7k7p5A2AdHni2X0SE1VDq-hvQ",
    "ie_key": "YoutubeTab",
    "id": "PLZEkgohG7k7p5A2AdHni2X0SE1VDq-hvQ",
    "title": "Onision, Critique Of"
  },
  {
    "_type": "url",
    "url": "https://www.youtube.com/playlist?list=PLZEkgohG7k7qbKdiDldsnO1cqFV_gBh7P",
    "ie_key": "YoutubeTab",
    "id": "PLZEkgohG7k7qbKdiDldsnO1cqFV_gBh7P",
    "title": "OnlyFans, Commentary On"
  },
  {
    "_type": "url",
    "url": "https://www.youtube.com/playlist?list=PLZEkgohG7k7rxq7ZWTNY2QzcVHyAJp3aD",
    "ie_key": "YoutubeTab",
    "id": "PLZEkgohG7k7rxq7ZWTNY2QzcVHyAJp3aD",
    "title": "Palm Oil (Vegan Idiocy About)"
  },
  {
    "_type": "url",
    "url": "https://www.youtube.com/playlist?list=PLZEkgohG7k7qveC2LrsTcLdX06MTjM_jY",
    "ie_key": "YoutubeTab",
    "id": "PLZEkgohG7k7qveC2LrsTcLdX06MTjM_jY",
    "title": "Permanent Vacation and/or/as/vs. Vegan Activism"
  },
  {
    "_type": "url",
    "url": "https://www.youtube.com/playlist?list=PLZEkgohG7k7pWxfE-5QLh5AvTsFAC3nOQ",
    "ie_key": "YoutubeTab",
    "id": "PLZEkgohG7k7pWxfE-5QLh5AvTsFAC3nOQ",
    "title": "Peter Singer, Critique Of"
  },
  {
    "_type": "url",
    "url": "https://www.youtube.com/playlist?list=PLZEkgohG7k7pQaxWyvjc7XHvfsMLywBiw",
    "ie_key": "YoutubeTab",
    "id": "PLZEkgohG7k7pQaxWyvjc7XHvfsMLywBiw",
    "title": "Plant Based News (Critique of)"
  },
  {
    "_type": "url",
    "url": "https://www.youtube.com/playlist?list=PLZEkgohG7k7omGiM0fgRjqLvrOxf2iWAY",
    "ie_key": "YoutubeTab",
    "id": "PLZEkgohG7k7omGiM0fgRjqLvrOxf2iWAY",
    "title": "ProJared"
  },
  {
    "_type": "url",
    "url": "https://www.youtube.com/playlist?list=PLZEkgohG7k7p-NzEZNy8ttSBzZHCI7Iud",
    "ie_key": "YoutubeTab",
    "id": "PLZEkgohG7k7p-NzEZNy8ttSBzZHCI7Iud",
    "title": "Quit Video Games."
  },
  {
    "_type": "url",
    "url": "https://www.youtube.com/playlist?list=PLZEkgohG7k7rr7TxjwIaxe77Fj8y5o3Gk",
    "ie_key": "YoutubeTab",
    "id": "PLZEkgohG7k7rr7TxjwIaxe77Fj8y5o3Gk",
    "title": "Rachel Oates, critique of"
  },
  {
    "_type": "url",
    "url": "https://www.youtube.com/playlist?list=PLZEkgohG7k7otvz8UHrY0I58cacC2mzoD",
    "ie_key": "YoutubeTab",
    "id": "PLZEkgohG7k7otvz8UHrY0I58cacC2mzoD",
    "title": "Racism and/in Vegan Politics"
  },
  {
    "_type": "url",
    "url": "https://www.youtube.com/playlist?list=PLZEkgohG7k7r1UtbvF7Xo_ZhB-t722W0-",
    "ie_key": "YoutubeTab",
    "id": "PLZEkgohG7k7r1UtbvF7Xo_ZhB-t722W0-",
    "title": "Racism: How to End Racism."
  },
  {
    "_type": "url",
    "url": "https://www.youtube.com/playlist?list=PLZEkgohG7k7qGb4Be2LkDxG4hetoMHL5f",
    "ie_key": "YoutubeTab",
    "id": "PLZEkgohG7k7qGb4Be2LkDxG4hetoMHL5f",
    "title": "Rap Music / Hip Hop (Commentary)"
  },
  {
    "_type": "url",
    "url": "https://www.youtube.com/playlist?list=PLZEkgohG7k7q8Q1UqKT1pKS_2vj31Wjmg",
    "ie_key": "YoutubeTab",
    "id": "PLZEkgohG7k7q8Q1UqKT1pKS_2vj31Wjmg",
    "title": "Rationality Rules, critique of"
  },
  {
    "_type": "url",
    "url": "https://www.youtube.com/playlist?list=PLZEkgohG7k7olkSedSBmPg2xkapErjden",
    "ie_key": "YoutubeTab",
    "id": "PLZEkgohG7k7olkSedSBmPg2xkapErjden",
    "title": "Refuting Libertarianism, Anarchism, etc."
  },
  {
    "_type": "url",
    "url": "https://www.youtube.com/playlist?list=PLZEkgohG7k7pRE2IeE9hQuIgtazIbOHTH",
    "ie_key": "YoutubeTab",
    "id": "PLZEkgohG7k7pRE2IeE9hQuIgtazIbOHTH",
    "title": "Replace Christmas"
  },
  {
    "_type": "url",
    "url": "https://www.youtube.com/playlist?list=PLZEkgohG7k7olnCFifop4r9ZWSgM1Jps8",
    "ie_key": "YoutubeTab",
    "id": "PLZEkgohG7k7olnCFifop4r9ZWSgM1Jps8",
    "title": "Repzion, \"Commentary\""
  },
  {
    "_type": "url",
    "url": "https://www.youtube.com/playlist?list=PLZEkgohG7k7oivCxCzg3NeBufsGUxmtv0",
    "ie_key": "YoutubeTab",
    "id": "PLZEkgohG7k7oivCxCzg3NeBufsGUxmtv0",
    "title": "Richard Wolff, Critique Of"
  },
  {
    "_type": "url",
    "url": "https://www.youtube.com/playlist?list=PLZEkgohG7k7o-Pd7AbjGZ59rZsfcotXOT",
    "ie_key": "YoutubeTab",
    "id": "PLZEkgohG7k7o-Pd7AbjGZ59rZsfcotXOT",
    "title": "Sam Harris is Wrong: Theravada Buddhism"
  },
  {
    "_type": "url",
    "url": "https://www.youtube.com/playlist?list=PLZEkgohG7k7r9E5IlUfLiBrXiN5Q9Yflc",
    "ie_key": "YoutubeTab",
    "id": "PLZEkgohG7k7r9E5IlUfLiBrXiN5Q9Yflc",
    "title": "Sarah's Vegan Kitchen, Sarah Sullivan"
  },
  {
    "_type": "url",
    "url": "https://www.youtube.com/playlist?list=PLZEkgohG7k7qvqyo8mxHc54fAaFVWiuUN",
    "ie_key": "YoutubeTab",
    "id": "PLZEkgohG7k7qvqyo8mxHc54fAaFVWiuUN",
    "title": "Satire is not comedy"
  },
  {
    "_type": "url",
    "url": "https://www.youtube.com/playlist?list=PLZEkgohG7k7qjSyAPLuO26oXBYA-3doIh",
    "ie_key": "YoutubeTab",
    "id": "PLZEkgohG7k7qjSyAPLuO26oXBYA-3doIh",
    "title": "Second-hand leather (critique of excuses for)"
  },
  {
    "_type": "url",
    "url": "https://www.youtube.com/playlist?list=PLZEkgohG7k7r9Ov3-KeJFaRzQdmRr6jFU",
    "ie_key": "YoutubeTab",
    "id": "PLZEkgohG7k7r9Ov3-KeJFaRzQdmRr6jFU",
    "title": "Shane Dawson, \"commentary\""
  },
  {
    "_type": "url",
    "url": "https://www.youtube.com/playlist?list=PLZEkgohG7k7oKzZ7jZNuZ81v57gL5fFHx",
    "ie_key": "YoutubeTab",
    "id": "PLZEkgohG7k7oKzZ7jZNuZ81v57gL5fFHx",
    "title": "So-called \"Nation Rising\" (Canadian Vegan Movement)"
  },
  {
    "_type": "url",
    "url": "https://www.youtube.com/playlist?list=PLZEkgohG7k7qg5zmJyFasMn3W6tOwmDWt",
    "ie_key": "YoutubeTab",
    "id": "PLZEkgohG7k7qg5zmJyFasMn3W6tOwmDWt",
    "title": "Social Justice: Veganism is NOT a Social Justice Movement."
  },
  {
    "_type": "url",
    "url": "https://www.youtube.com/playlist?list=PLZEkgohG7k7pWJbIvgr3KScwTgP4x2ZfW",
    "ie_key": "YoutubeTab",
    "id": "PLZEkgohG7k7pWJbIvgr3KScwTgP4x2ZfW",
    "title": "Star Wars, Critique Of."
  },
  {
    "_type": "url",
    "url": "https://www.youtube.com/playlist?list=PLZEkgohG7k7qsVwwjxWvfx9LPx4_phmjm",
    "ie_key": "YoutubeTab",
    "id": "PLZEkgohG7k7qsVwwjxWvfx9LPx4_phmjm",
    "title": "Start Your Own Youtube Channel, How You Should"
  },
  {
    "_type": "url",
    "url": "https://www.youtube.com/playlist?list=PLZEkgohG7k7qSHqXh0JLF9Z-3uXfI4TOu",
    "ie_key": "YoutubeTab",
    "id": "PLZEkgohG7k7qSHqXh0JLF9Z-3uXfI4TOu",
    "title": "Stefan Molyneux, critique of"
  },
  {
    "_type": "url",
    "url": "https://www.youtube.com/playlist?list=PLZEkgohG7k7pRF4EDdFKpdQlHEd2-xPM_",
    "ie_key": "YoutubeTab",
    "id": "PLZEkgohG7k7pRF4EDdFKpdQlHEd2-xPM_",
    "title": "Stop Treating Women Like Infants"
  },
  {
    "_type": "url",
    "url": "https://www.youtube.com/playlist?list=PLZEkgohG7k7p_HR6tI18g886Y6KbR1Ss1",
    "ie_key": "YoutubeTab",
    "id": "PLZEkgohG7k7p_HR6tI18g886Y6KbR1Ss1",
    "title": "Supreme Banana (Cammy), Critique Of"
  },
  {
    "_type": "url",
    "url": "https://www.youtube.com/playlist?list=PLZEkgohG7k7ro3IVau5JjbIs-aywDCI2b",
    "ie_key": "YoutubeTab",
    "id": "PLZEkgohG7k7ro3IVau5JjbIs-aywDCI2b",
    "title": "Sv3rige, Critique Of"
  },
  {
    "_type": "url",
    "url": "https://www.youtube.com/playlist?list=PLZEkgohG7k7rStbYGdBRzEgyPVm3RHqMT",
    "ie_key": "YoutubeTab",
    "id": "PLZEkgohG7k7rStbYGdBRzEgyPVm3RHqMT",
    "title": "THE SHORT LIST: my approach to veganism IN BRIEF."
  },
  {
    "_type": "url",
    "url": "https://www.youtube.com/playlist?list=PLZEkgohG7k7pT2VULD2abhlVRlXy80uk2",
    "ie_key": "YoutubeTab",
    "id": "PLZEkgohG7k7pT2VULD2abhlVRlXy80uk2",
    "title": "Ted Carr, A Critique of the Permanent Vacation Philosophy."
  },
  {
    "_type": "url",
    "url": "https://www.youtube.com/playlist?list=PLZEkgohG7k7piCYbp0Wz5eWCAErv7BaCl",
    "ie_key": "YoutubeTab",
    "id": "PLZEkgohG7k7piCYbp0Wz5eWCAErv7BaCl",
    "title": "The Amazing Atheist, critique of (T.J. Kirk)"
  },
  {
    "_type": "url",
    "url": "https://www.youtube.com/playlist?list=PLZEkgohG7k7oJ7h972jt2ywhYwxn4ZZfH",
    "ie_key": "YoutubeTab",
    "id": "PLZEkgohG7k7oJ7h972jt2ywhYwxn4ZZfH",
    "title": "The Economics of Inequality."
  },
  {
    "_type": "url",
    "url": "https://www.youtube.com/playlist?list=PLZEkgohG7k7qBcdsS92pcavRN93nO22_0",
    "ie_key": "YoutubeTab",
    "id": "PLZEkgohG7k7qBcdsS92pcavRN93nO22_0",
    "title": "The Meaning of Life. Not Clickbait."
  },
  {
    "_type": "url",
    "url": "https://www.youtube.com/playlist?list=PLZEkgohG7k7rYZSBO1zk-7qROjFAb1Dtb",
    "ie_key": "YoutubeTab",
    "id": "PLZEkgohG7k7rYZSBO1zk-7qROjFAb1Dtb",
    "title": "The State of Youtube (Analysis of)"
  },
  {
    "_type": "url",
    "url": "https://www.youtube.com/playlist?list=PLZEkgohG7k7rsfQC1dCIBlGs3eOzSb1b_",
    "ie_key": "YoutubeTab",
    "id": "PLZEkgohG7k7rsfQC1dCIBlGs3eOzSb1b_",
    "title": "Therapy (Therapists, Psychiatrists, etc.)"
  },
  {
    "_type": "url",
    "url": "https://www.youtube.com/playlist?list=PLZEkgohG7k7oKlvnSlR6nX9UdACEUJ7fn",
    "ie_key": "YoutubeTab",
    "id": "PLZEkgohG7k7oKlvnSlR6nX9UdACEUJ7fn",
    "title": "Transgender-ism, trans rights, transphobia."
  },
  {
    "_type": "url",
    "url": "https://www.youtube.com/playlist?list=PLZEkgohG7k7pJVoecem-78B_an41D0HlH",
    "ie_key": "YoutubeTab",
    "id": "PLZEkgohG7k7pJVoecem-78B_an41D0HlH",
    "title": "True Love / True Romance (Advice?)"
  },
  {
    "_type": "url",
    "url": "https://www.youtube.com/playlist?list=PLZEkgohG7k7o__EMYPCrQdWWLnBNmxvf7",
    "ie_key": "YoutubeTab",
    "id": "PLZEkgohG7k7o__EMYPCrQdWWLnBNmxvf7",
    "title": "Trump, Epstein & Katie Johnson"
  },
  {
    "_type": "url",
    "url": "https://www.youtube.com/playlist?list=PLZEkgohG7k7r1q2Qfive2T4mvHLVmqam7",
    "ie_key": "YoutubeTab",
    "id": "PLZEkgohG7k7r1q2Qfive2T4mvHLVmqam7",
    "title": "Truth Crab, Interviews and Discussions With"
  },
  {
    "_type": "url",
    "url": "https://www.youtube.com/playlist?list=PLZEkgohG7k7q4UfL8k99S7kLax-tGUmnU",
    "ie_key": "YoutubeTab",
    "id": "PLZEkgohG7k7q4UfL8k99S7kLax-tGUmnU",
    "title": "University Education, Critique Of"
  },
  {
    "_type": "url",
    "url": "https://www.youtube.com/playlist?list=PLZEkgohG7k7q1tG0m8UNDqbYFg45Bc93a",
    "ie_key": "YoutubeTab",
    "id": "PLZEkgohG7k7q1tG0m8UNDqbYFg45Bc93a",
    "title": "Unnatural Vegan (Criticism Of)"
  },
  {
    "_type": "url",
    "url": "https://www.youtube.com/playlist?list=PLZEkgohG7k7q-pi74aOPFBMJfVrKH-HFx",
    "ie_key": "YoutubeTab",
    "id": "PLZEkgohG7k7q-pi74aOPFBMJfVrKH-HFx",
    "title": "Utilitarianism, critique of"
  },
  {
    "_type": "url",
    "url": "https://www.youtube.com/playlist?list=PLZEkgohG7k7pnXbGGW6WCZBnaoLxLjuhJ",
    "ie_key": "YoutubeTab",
    "id": "PLZEkgohG7k7pnXbGGW6WCZBnaoLxLjuhJ",
    "title": "Vaush, critique of"
  },
  {
    "_type": "url",
    "url": "https://www.youtube.com/playlist?list=PLZEkgohG7k7q3qn7RiaVrYAlndkH4VuKq",
    "ie_key": "YoutubeTab",
    "id": "PLZEkgohG7k7q3qn7RiaVrYAlndkH4VuKq",
    "title": "Vegan Cheetah, Conversations With"
  },
  {
    "_type": "url",
    "url": "https://www.youtube.com/playlist?list=PLZEkgohG7k7o-xDppIDvXLZziqoNILs5m",
    "ie_key": "YoutubeTab",
    "id": "PLZEkgohG7k7o-xDppIDvXLZziqoNILs5m",
    "title": "Vegan Mind Tricks: Talking to Meat Eaters."
  },
  {
    "_type": "url",
    "url": "https://www.youtube.com/playlist?list=PLZEkgohG7k7pperokk75ic6XpyLqy7MUw",
    "ie_key": "YoutubeTab",
    "id": "PLZEkgohG7k7pperokk75ic6XpyLqy7MUw",
    "title": "Vegan Storybook (For Children), \"Even Earthworms Want to See the Sky\""
  },
  {
    "_type": "url",
    "url": "https://www.youtube.com/playlist?list=PLZEkgohG7k7ptYOxvjmMhJ6CnRUJWgkwt",
    "ie_key": "YoutubeTab",
    "id": "PLZEkgohG7k7ptYOxvjmMhJ6CnRUJWgkwt",
    "title": "Vegan Youtube, state of the demimonde"
  },
  {
    "_type": "url",
    "url": "https://www.youtube.com/playlist?list=PLZEkgohG7k7qrHC5-UQDpMKvEmQjPiTTv",
    "ie_key": "YoutubeTab",
    "id": "PLZEkgohG7k7qrHC5-UQDpMKvEmQjPiTTv",
    "title": "Veganism: the Wildlife Management Paradigm"
  },
  {
    "_type": "url",
    "url": "https://www.youtube.com/playlist?list=PLZEkgohG7k7pkLltX-SJOXayJTAz__yIl",
    "ie_key": "YoutubeTab",
    "id": "PLZEkgohG7k7pkLltX-SJOXayJTAz__yIl",
    "title": "Vietnam War, My Opinion on the History of the"
  },
  {
    "_type": "url",
    "url": "https://www.youtube.com/playlist?list=PLZEkgohG7k7oUy246Vd6jhIo4UoXJFhaE",
    "ie_key": "YoutubeTab",
    "id": "PLZEkgohG7k7oUy246Vd6jhIo4UoXJFhaE",
    "title": "Vs. Ex-Vegan Jacko Wacko Vegano"
  },
  {
    "_type": "url",
    "url": "https://www.youtube.com/playlist?list=PLZEkgohG7k7oCYd-6JuqPkFnQxk8Ms7Sy",
    "ie_key": "YoutubeTab",
    "id": "PLZEkgohG7k7oCYd-6JuqPkFnQxk8Ms7Sy",
    "title": "Why I Do Youtube."
  },
  {
    "_type": "url",
    "url": "https://www.youtube.com/playlist?list=PLZEkgohG7k7o2JRtjAER_kEI4lJym1Dsj",
    "ie_key": "YoutubeTab",
    "id": "PLZEkgohG7k7o2JRtjAER_kEI4lJym1Dsj",
    "title": "[ESL中国] Advice on Teaching English in China"
  }
]
